chromedriver_autoupdate/__init__.py
chromedriver_autoupdate/driver_check.py
chromedriver_autoupdate-1.2.0.dist-info/LICENSE
chromedriver_autoupdate-1.2.0.dist-info/METADATA
chromedriver_autoupdate-1.2.0.dist-info/WHEEL
chromedriver_autoupdate-1.2.0.dist-info/top_level.txt
chromedriver_autoupdate-1.2.0.dist-info/RECORD
