Metadata-Version: 2.1
Name: chromedriver_autoupdate
Version: 1.2.0
Summary: chromedriver的自动更新
Home-page: https://github.com/roiding/chromedriver-autoupdate
Author: roiding
Author-email: maodoulove19950815@gmail.com
Classifier: Programming Language :: Python :: 3
Classifier: License :: OSI Approved :: GNU General Public License v3 (GPLv3)
Classifier: Operating System :: OS Independent
Requires-Python: >=3.6
License-File: LICENSE
Requires-Dist: requests
Requires-Dist: tqdm
